{
	"partitions" : [
		{
			"name" : "Top",
			"pins" : [
				{
					"name" : "HEX2[0]",
					"strict" : false
				},
				{
					"name" : "HEX2[1]",
					"strict" : false
				},
				{
					"name" : "HEX2[2]",
					"strict" : false
				},
				{
					"name" : "HEX2[3]",
					"strict" : false
				},
				{
					"name" : "HEX2[4]",
					"strict" : false
				},
				{
					"name" : "HEX2[5]",
					"strict" : false
				},
				{
					"name" : "HEX2[6]",
					"strict" : false
				},
				{
					"name" : "HEX4[0]",
					"strict" : false
				},
				{
					"name" : "HEX4[2]",
					"strict" : false
				},
				{
					"name" : "HEX4[3]",
					"strict" : false
				},
				{
					"name" : "HEX4[4]",
					"strict" : false
				},
				{
					"name" : "HEX4[5]",
					"strict" : false
				},
				{
					"name" : "HEX4[6]",
					"strict" : false
				},
				{
					"name" : "regTestOut[0]",
					"strict" : false
				},
				{
					"name" : "regTestOut[1]",
					"strict" : false
				},
				{
					"name" : "regTestOut[2]",
					"strict" : false
				},
				{
					"name" : "regTestOut[3]",
					"strict" : false
				},
				{
					"name" : "regTestOut[4]",
					"strict" : false
				},
				{
					"name" : "regTestOut[5]",
					"strict" : false
				},
				{
					"name" : "regTestOut[6]",
					"strict" : false
				},
				{
					"name" : "regTestOut[7]",
					"strict" : false
				},
				{
					"name" : "regTestOut[8]",
					"strict" : false
				},
				{
					"name" : "regTestOut[9]",
					"strict" : false
				},
				{
					"name" : "regTestOut[10]",
					"strict" : false
				},
				{
					"name" : "regTestOut[11]",
					"strict" : false
				},
				{
					"name" : "regTestOut[12]",
					"strict" : false
				},
				{
					"name" : "regTestOut[13]",
					"strict" : false
				},
				{
					"name" : "regTestOut[14]",
					"strict" : false
				},
				{
					"name" : "regTestOut[15]",
					"strict" : false
				},
				{
					"name" : "regTestOut[16]",
					"strict" : false
				},
				{
					"name" : "regTestOut[17]",
					"strict" : false
				},
				{
					"name" : "regTestOut[18]",
					"strict" : false
				},
				{
					"name" : "regTestOut[19]",
					"strict" : false
				},
				{
					"name" : "regTestOut[20]",
					"strict" : false
				},
				{
					"name" : "regTestOut[21]",
					"strict" : false
				},
				{
					"name" : "regTestOut[22]",
					"strict" : false
				},
				{
					"name" : "regTestOut[23]",
					"strict" : false
				},
				{
					"name" : "regTestOut[24]",
					"strict" : false
				},
				{
					"name" : "regTestOut[25]",
					"strict" : false
				},
				{
					"name" : "regTestOut[26]",
					"strict" : false
				},
				{
					"name" : "regTestOut[27]",
					"strict" : false
				},
				{
					"name" : "regTestOut[28]",
					"strict" : false
				},
				{
					"name" : "regTestOut[29]",
					"strict" : false
				},
				{
					"name" : "regTestOut[30]",
					"strict" : false
				},
				{
					"name" : "regTestOut[31]",
					"strict" : false
				},
				{
					"name" : "memTestOut[0]",
					"strict" : false
				},
				{
					"name" : "memTestOut[1]",
					"strict" : false
				},
				{
					"name" : "memTestOut[2]",
					"strict" : false
				},
				{
					"name" : "memTestOut[3]",
					"strict" : false
				},
				{
					"name" : "memTestOut[16]",
					"strict" : false
				},
				{
					"name" : "memTestOut[18]",
					"strict" : false
				},
				{
					"name" : "memTestOut[23]",
					"strict" : false
				},
				{
					"name" : "memTestOut[26]",
					"strict" : false
				},
				{
					"name" : "memTestOut[27]",
					"strict" : false
				},
				{
					"name" : "memTestOut[31]",
					"strict" : false
				},
				{
					"name" : "regTestEndOut[0]",
					"strict" : false
				},
				{
					"name" : "regTestEndOut[1]",
					"strict" : false
				},
				{
					"name" : "regTestEndOut[2]",
					"strict" : false
				},
				{
					"name" : "regTestEndOut[3]",
					"strict" : false
				},
				{
					"name" : "regTestEndOut[4]",
					"strict" : false
				},
				{
					"name" : "memTestEndOut[0]",
					"strict" : false
				},
				{
					"name" : "memTestEndOut[1]",
					"strict" : false
				},
				{
					"name" : "memTestEndOut[2]",
					"strict" : false
				},
				{
					"name" : "memTestEndOut[3]",
					"strict" : false
				},
				{
					"name" : "memTestEndOut[4]",
					"strict" : false
				},
				{
					"name" : "memTestEndOut[5]",
					"strict" : false
				},
				{
					"name" : "memTestEndOut[6]",
					"strict" : false
				},
				{
					"name" : "memTestEndOut[7]",
					"strict" : false
				},
				{
					"name" : "memTestEndOut[8]",
					"strict" : false
				},
				{
					"name" : "memTestEndOut[9]",
					"strict" : false
				},
				{
					"name" : "memTestEndOut[10]",
					"strict" : false
				},
				{
					"name" : "memTestEndOut[11]",
					"strict" : false
				},
				{
					"name" : "memTestEndOut[12]",
					"strict" : false
				},
				{
					"name" : "memTestEndOut[13]",
					"strict" : false
				},
				{
					"name" : "memTestEndOut[14]",
					"strict" : false
				},
				{
					"name" : "memTestEndOut[15]",
					"strict" : false
				},
				{
					"name" : "memTestEndOut[16]",
					"strict" : false
				},
				{
					"name" : "memTestEndOut[17]",
					"strict" : false
				},
				{
					"name" : "memTestEndOut[18]",
					"strict" : false
				},
				{
					"name" : "memTestEndOut[19]",
					"strict" : false
				},
				{
					"name" : "memTestEndOut[20]",
					"strict" : false
				},
				{
					"name" : "memTestEndOut[21]",
					"strict" : false
				},
				{
					"name" : "memTestEndOut[22]",
					"strict" : false
				},
				{
					"name" : "memTestEndOut[23]",
					"strict" : false
				},
				{
					"name" : "memTestEndOut[24]",
					"strict" : false
				},
				{
					"name" : "memTestEndOut[25]",
					"strict" : false
				},
				{
					"name" : "memTestEndOut[26]",
					"strict" : false
				},
				{
					"name" : "memTestEndOut[27]",
					"strict" : false
				},
				{
					"name" : "memTestEndOut[28]",
					"strict" : false
				},
				{
					"name" : "memTestEndOut[29]",
					"strict" : false
				},
				{
					"name" : "memTestEndOut[30]",
					"strict" : false
				},
				{
					"name" : "memTestEndOut[31]",
					"strict" : false
				},
				{
					"name" : "regEnd[1]",
					"strict" : false
				},
				{
					"name" : "regEnd[3]",
					"strict" : false
				},
				{
					"name" : "regEnd[2]",
					"strict" : false
				},
				{
					"name" : "regEnd[0]",
					"strict" : false
				},
				{
					"name" : "memEnd[0]",
					"strict" : false
				},
				{
					"name" : "memEnd[1]",
					"strict" : false
				},
				{
					"name" : "memEnd[2]",
					"strict" : false
				},
				{
					"name" : "memEnd[3]",
					"strict" : false
				},
				{
					"name" : "regEnd[4]",
					"strict" : false
				},
				{
					"name" : "memEnd[4]",
					"strict" : false
				},
				{
					"name" : "memEnd[5]",
					"strict" : false
				},
				{
					"name" : "memEnd[6]",
					"strict" : false
				},
				{
					"name" : "memEnd[7]",
					"strict" : false
				},
				{
					"name" : "memEnd[8]",
					"strict" : false
				},
				{
					"name" : "memEnd[9]",
					"strict" : false
				},
				{
					"name" : "memEnd[10]",
					"strict" : false
				},
				{
					"name" : "memEnd[11]",
					"strict" : false
				},
				{
					"name" : "memEnd[12]",
					"strict" : false
				},
				{
					"name" : "memEnd[13]",
					"strict" : false
				},
				{
					"name" : "memEnd[14]",
					"strict" : false
				},
				{
					"name" : "memEnd[15]",
					"strict" : false
				},
				{
					"name" : "memEnd[16]",
					"strict" : false
				},
				{
					"name" : "memEnd[17]",
					"strict" : false
				},
				{
					"name" : "memEnd[18]",
					"strict" : false
				},
				{
					"name" : "memEnd[19]",
					"strict" : false
				},
				{
					"name" : "memEnd[20]",
					"strict" : false
				},
				{
					"name" : "memEnd[21]",
					"strict" : false
				},
				{
					"name" : "memEnd[22]",
					"strict" : false
				},
				{
					"name" : "memEnd[23]",
					"strict" : false
				},
				{
					"name" : "memEnd[24]",
					"strict" : false
				},
				{
					"name" : "memEnd[25]",
					"strict" : false
				},
				{
					"name" : "memEnd[26]",
					"strict" : false
				},
				{
					"name" : "memEnd[27]",
					"strict" : false
				},
				{
					"name" : "memEnd[28]",
					"strict" : false
				},
				{
					"name" : "memEnd[29]",
					"strict" : false
				},
				{
					"name" : "memEnd[30]",
					"strict" : false
				},
				{
					"name" : "memEnd[31]",
					"strict" : false
				},
				{
					"name" : "clk",
					"strict" : false
				}
			]
		}
	]
}